monolithium/Cargo.toml
monolithium/__init__.py
monolithium/__main__.py
monolithium/meson.build
monolithium/statistics.py
monolithium/.cargo/config.toml
monolithium/monolithium/lib.rs
monolithium/monolithium/main.cu
monolithium/monolithium/main.rs
monolithium/monolithium/monolith.rs
monolithium/monolithium/perlin.rs
monolithium/monolithium/rng.rs
monolithium/monolithium/seeds.rs
monolithium/monolithium/utils.rs
monolithium/monolithium/world.rs
monolithium/monolithium/commands/mask.rs
monolithium/monolithium/commands/mod.rs
monolithium/monolithium/commands/perlin.rs
monolithium/monolithium/commands/search.rs
monolithium/resources/images/logo.png
monolithium/resources/images/logo.svg
monolithium-1.2.0.dist-info/METADATA
monolithium-1.2.0.dist-info/WHEEL
monolithium-1.2.0.dist-info/entry_points.txt
monolithium-1.2.0.dist-info/RECORD
