Metadata-Version: 2.4
Name: monolithium
Version: 1.2.0
Summary: Finding the Largest Minecraft Alpha Monoliths
Project-URL: GitHub, https://github.com/Tremeschin/Monolithium
Author: Tremeschin
License-Expression: MIT
Requires-Python: >=3.10
Requires-Dist: meson
Requires-Dist: ninja
Requires-Dist: rustbin
Requires-Dist: tomli
Provides-Extra: all
Requires-Dist: altair; extra == 'all'
Requires-Dist: attrs; extra == 'all'
Requires-Dist: mkdocs-material~=9.6.22; extra == 'all'
Requires-Dist: mkdocs~=1.6.1; extra == 'all'
Requires-Dist: numpy; extra == 'all'
Requires-Dist: scipy; extra == 'all'
Requires-Dist: vl-convert-python; extra == 'all'
Provides-Extra: statistics
Requires-Dist: altair; extra == 'statistics'
Requires-Dist: attrs; extra == 'statistics'
Requires-Dist: numpy; extra == 'statistics'
Requires-Dist: scipy; extra == 'statistics'
Requires-Dist: vl-convert-python; extra == 'statistics'
Provides-Extra: website
Requires-Dist: mkdocs-material~=9.6.22; extra == 'website'
Requires-Dist: mkdocs~=1.6.1; extra == 'website'
